{
  "gitSyncId": "67f1d38f32ca7555311f058e_fa339ac4-aeb7-4070-98c6-270a98ef19d6",
  "id": "Petly Landing Page_JSObject1.myFun2",
  "pluginId": "js-plugin",
  "pluginType": "JS",
  "unpublishedAction": {
    "actionConfiguration": {
      "encodeParamsToggle": true,
      "jsArguments": [],
      "paginationType": "NONE",
      "timeoutInMillisecond": 10000
    },
    "clientSideExecution": true,
    "collectionId": "Petly Landing Page_JSObject1",
    "confirmBeforeExecute": false,
    "datasource": {
      "isAutoGenerated": false,
      "name": "UNUSED_DATASOURCE",
      "pluginId": "js-plugin"
    },
    "dynamicBindingPathList": [
      {
        "key": "body"
      }
    ],
    "executeOnLoad": false,
    "fullyQualifiedName": "JSObject1.myFun2",
    "name": "myFun2",
    "pageId": "Petly Landing Page",
    "userSetOnLoad": false
  }
}